boolsched/__init__.py
boolsched/schedule.py
boolsched-0.2.0.dist-info/METADATA
boolsched-0.2.0.dist-info/WHEEL
boolsched-0.2.0.dist-info/licenses/LICENSE.txt
boolsched-0.2.0.dist-info/RECORD
