Metadata-Version: 2.3
Name: boolsched
Version: 0.2.0
Summary: A programmatic, composable scheduling system using boolean logic
Project-URL: homepage, https://github.com/hchargois/boolsched
Author-email: Hugo Chargois <hugo.chargois@free.fr>
License-File: LICENSE.txt
Classifier: License :: OSI Approved :: MIT License
Classifier: Operating System :: OS Independent
Classifier: Programming Language :: Python :: 3
Requires-Python: >=3.10
